fundalytica_utils/__init__.py
fundalytica_utils/data.py
fundalytica_utils/mailer.py
fundalytica_utils/stock.py
fundalytica_utils/utils.py
fundalytica_utils-0.0.5.dist-info/LICENSE
fundalytica_utils-0.0.5.dist-info/METADATA
fundalytica_utils-0.0.5.dist-info/WHEEL
fundalytica_utils-0.0.5.dist-info/top_level.txt
fundalytica_utils-0.0.5.dist-info/RECORD
