Metadata-Version: 2.1
Name: fundalytica-utils
Version: 0.0.5
Summary: Fundalytica Utils
Home-page: https://github.com/fundalytica/utils
Author: Fotios Dotcom
Author-email: fotios@fundalytica.com
License: UNKNOWN
Platform: UNKNOWN
Classifier: Programming Language :: Python :: 3
Classifier: License :: OSI Approved :: MIT License
Classifier: Operating System :: OS Independent
Requires-Python: >=3.8
License-File: LICENSE
